{
  "credit": "Made with Blockbench",
  "texture_size": [
    128,
    128
  ],
  "textures": {
    "0": "jta:block/black_pole",
    "particle": "jta:block/black_pole"
  },
  "elements": [
    {
      "from": [
        7.5,
        0,
        7.5
      ],
      "to": [
        8.5,
        16,
        8.5
      ],
      "rotation": {
        "angle": 22.5,
        "axis": "y",
        "origin": [
          7,
          0,
          5
        ]
      },
      "faces": {
        "north": {
          "uv": [
            0,
            0,
            1,
            16
          ],
          "texture": "#0"
        },
        "east": {
          "uv": [
            7,
            0,
            8,
            16
          ],
          "texture": "#0"
        },
        "south": {
          "uv": [
            1,
            0,
            2,
            16
          ],
          "texture": "#0"
        },
        "west": {
          "uv": [
            6,
            0,
            7,
            16
          ],
          "texture": "#0"
        },
        "up": {
          "uv": [
            2.125,
            0,
            3.125,
            1
          ],
          "texture": "#0"
        },
        "down": {
          "uv": [
            5,
            0,
            6,
            1
          ],
          "texture": "#0"
        }
      }
    }
  ],
  "display": {
    "thirdperson_righthand": {
      "rotation": [
        0,
        180,
        0
      ]
    },
    "thirdperson_lefthand": {
      "rotation": [
        0,
        180,
        0
      ]
    },
    "firstperson_righthand": {
      "rotation": [
        0,
        180,
        0
      ],
      "translation": [
        0,
        0,
        -2
      ]
    },
    "firstperson_lefthand": {
      "rotation": [
        0,
        180,
        0
      ]
    },
    "gui": {
      "rotation": [
        0,
        180,
        0
      ]
    },
    "head": {
      "translation": [
        0,
        10,
        0
      ]
    }
  }
}